.gitignore
.travis.yml
CHANGES
MANIFEST.in
README.rst
nose2.cfg
requirements.txt
setup.py
fakechroot/__init__.py
fakechroot/fakechroot.py
fakechroot/lock.py
fakechroot/tests.py
fakechroot/unittest2.py
fakechroot.egg-info/PKG-INFO
fakechroot.egg-info/SOURCES.txt
fakechroot.egg-info/dependency_links.txt
fakechroot.egg-info/not-zip-safe
fakechroot.egg-info/requires.txt
fakechroot.egg-info/top_level.txt
fakechroot/overlay/env
fakechroot/overlay/sudo