Metadata-Version: 1.0
Name: fakechroot
Version: 0.2.1
Summary: A fixture for using a fakechroot environment in your tests
Home-page: http://github.com/yaybu/fakechroot
Author: John Carr
Author-email: john.carr@isotoma.com
License: Apache Software License
Platform: UNKNOWN
Classifier: Intended Audience :: Developers
Classifier: Operating System :: POSIX
Classifier: License :: OSI Approved :: Apache Software License
Classifier: Programming Language :: Python :: 2
Classifier: Programming Language :: Python :: 2.6
Classifier: Programming Language :: Python :: 2.7
Classifier: Programming Language :: Python :: 3
Classifier: Programming Language :: Python :: 3.3
Classifier: Programming Language :: Python :: 3.4
Classifier: Programming Language :: Python :: Implementation :: CPython
Classifier: Programming Language :: Python :: Implementation :: PyPy
